tools/__init__.py
tools/main.py
tools/dtos/__init__.py
tools/dtos/aws_var.py
tools/dtos/jump_var.py
tools/dtos/k8_var.py
tools/dtos/ssh_var.py
tools/dtos/utill_var.py
tools/functions/__init__.py
tools/functions/aws.py
tools/functions/jump.py
tools/functions/k8.py
tools/functions/ssh.py
tools/utils/__init__.py
tools/utils/k8_utils.py
tools/utils/utils.py
devops_auto_tools-1.3.5.dist-info/METADATA
devops_auto_tools-1.3.5.dist-info/WHEEL
devops_auto_tools-1.3.5.dist-info/entry_points.txt
devops_auto_tools-1.3.5.dist-info/top_level.txt
devops_auto_tools-1.3.5.dist-info/RECORD
