Metadata-Version: 2.1
Name: devops-auto-tools
Version: 1.3.5
Summary: A Python project using cli: eksm, sshm, jumpm, k8m for devops expert
Author: Baristi Trieu
Author-email: ltqtrieu.0204@gmail.com
License: MIT
Classifier: Development Status :: 5 - Production/Stable
Classifier: Intended Audience :: Science/Research
Classifier: Operating System :: POSIX :: Linux
Classifier: Programming Language :: Python :: 3.8
Requires-Dist: simple-term-menu ==1.4.1
Requires-Dist: sshuttle ==1.1.1
Requires-Dist: requests ==2.31.0
Requires-Dist: pyyaml ==6.0.1
Requires-Dist: PyJWT ==2.8.0
